setwallpaper/__init__.py
setwallpaper/wallpaper.py
setwallpaper/win.py
setwallpaper-0.0.1.dist-info/LICENSE
setwallpaper-0.0.1.dist-info/METADATA
setwallpaper-0.0.1.dist-info/WHEEL
setwallpaper-0.0.1.dist-info/top_level.txt
setwallpaper-0.0.1.dist-info/RECORD
